LICENSE
README.rst
setup.py
docs/HISTORY.txt
docs/INSTALL.txt
docs/LICENSE.GPL
docs/LICENSE.txt
quintagroup/__init__.py
quintagroup.slidertemplates.egg-info/PKG-INFO
quintagroup.slidertemplates.egg-info/SOURCES.txt
quintagroup.slidertemplates.egg-info/dependency_links.txt
quintagroup.slidertemplates.egg-info/entry_points.txt
quintagroup.slidertemplates.egg-info/namespace_packages.txt
quintagroup.slidertemplates.egg-info/not-zip-safe
quintagroup.slidertemplates.egg-info/requires.txt
quintagroup.slidertemplates.egg-info/top_level.txt
quintagroup/slidertemplates/__init__.py
quintagroup/slidertemplates/configure.zcml
quintagroup/slidertemplates/tests.py
quintagroup/slidertemplates/browser/__init__.py
quintagroup/slidertemplates/browser/configure.zcml
quintagroup/slidertemplates/browser/static/slidertemplates-compiled.css
quintagroup/slidertemplates/browser/static/css/slidertemplates.less
quintagroup/slidertemplates/browser/static/js/circleCarousel.js
quintagroup/slidertemplates/browser/static/js/heightFix.js
quintagroup/slidertemplates/browser/static/js/owl_carousel.js
quintagroup/slidertemplates/browser/static/js/qgCarousel.js
quintagroup/slidertemplates/browser/static/js/tabs.js
quintagroup/slidertemplates/browser/templates/carousel.pt
quintagroup/slidertemplates/browser/templates/contentSlider.pt
quintagroup/slidertemplates/browser/templates/horizontal-tabs.pt
quintagroup/slidertemplates/browser/templates/qgCarousel.pt
quintagroup/slidertemplates/browser/templates/shelf.pt
quintagroup/slidertemplates/browser/templates/vertical-tabs.pt
quintagroup/slidertemplates/profiles/default/metadata.xml
quintagroup/slidertemplates/profiles/default/registry.xml
quintagroup/slidertemplates/profiles/uninstall/registry.xml