Metadata-Version: 1.0
Name: quintagroup.slidertemplates
Version: 1.5
Summary: Different Templates to display NGCollection Portlet
Home-page: http://svn.plone.org/svn/collective/
Author: UNKNOWN
Author-email: UNKNOWN
License: GPL
Platform: UNKNOWN
Classifier: Framework :: Plone
Classifier: Programming Language :: Python
